AUTHORS.txt
CHANGES.txt
FAQ.txt
INSTALL.txt
LICENSE.txt
MANIFEST.in
README.txt
TODO.txt
setup.py
docs/Makefile
docs/README.txt
docs/algorithm.rst
docs/conf.py
docs/description.rst
docs/grampg.rst
docs/index.rst
docs/make.bat
grampg/__init__.py
grampg/grampg.py
grampg.egg-info/PKG-INFO
grampg.egg-info/SOURCES.txt
grampg.egg-info/dependency_links.txt
grampg.egg-info/top_level.txt
grampg/demo/__init__.py
grampg/demo/many_passwords.py
grampg/tests/__init__.py
grampg/tests/regression.py
grampg/tests/tests.py
grampg/tests/usecases.py