Metadata-Version: 1.0
Name: grampg
Version: 0.3.0
Summary: Simple and flexible password generation library.
Home-page: https://bitbucket.org/etoccalino/grampg
Author: Elvio Toccalino
Author-email: me@etoccalino.com
License: GNU Affero General Public License (LICENSE.txt)
Keywords: grumpy admin password generator
Platform: UNKNOWN
